polish_trains/__init__.py
polish_trains/drivers.py
polish_trains/geckodriver
polish_trains/parsers.py
polish_trains-0.1.0.dist-info/WHEEL
polish_trains-0.1.0.dist-info/METADATA
polish_trains-0.1.0.dist-info/RECORD
