Metadata-Version: 2.1
Name: polish-trains
Version: 0.1.0
Summary: Search polish trains via simple API.
License: MIT
Author: Konrad Nowara
Requires-Python: >=3.10,<4.0
Classifier: License :: OSI Approved :: MIT License
Classifier: Programming Language :: Python :: 3
Classifier: Programming Language :: Python :: 3.10
Requires-Dist: async_generator (==1.10)
Requires-Dist: attrs (==21.2.0)
Requires-Dist: beautifulsoup4 (==4.10.0)
Requires-Dist: certifi (==2021.10.8)
Requires-Dist: cffi (==1.15.0)
Requires-Dist: cryptography (==35.0.0)
Requires-Dist: h11 (==0.12.0)
Requires-Dist: idna (==3.3)
Requires-Dist: outcome (==1.1.0)
Requires-Dist: pyOpenSSL (==21.0.0)
Requires-Dist: pycparser (==2.21)
Requires-Dist: selenium (==4.0.0)
Requires-Dist: six (==1.16.0)
Requires-Dist: sniffio (==1.2.0)
Requires-Dist: sortedcontainers (==2.4.0)
Requires-Dist: soupsieve (==2.3.1)
Requires-Dist: trio (==0.19.0)
Requires-Dist: trio-websocket (==0.9.2)
Requires-Dist: urllib3 (==1.26.7)
Requires-Dist: wsproto (==1.0.0)
